default_values-0.7.0.dist-info/LICENSE
default_values-0.7.0.dist-info/METADATA
default_values-0.7.0.dist-info/WHEEL
default_values-0.7.0.dist-info/entry_points.txt
sphinxcontrib/default_values/__init__.py
sphinxcontrib/default_values/demo.py
sphinxcontrib/default_values/py.typed
default_values-0.7.0.dist-info/RECORD
