Metadata-Version: 2.2
Name: default-values
Version: 0.7.0
Summary: Sphinx extension to show default values in documentation.
Author-email: Dominic Davis-Foster <dominic@davis-foster.co.uk>
License: MIT
Keywords: documentation,sphinx
Home-page: https://github.com/sphinx-toolbox/default_values
Project-URL: Issue Tracker, https://github.com/sphinx-toolbox/default_values/issues
Project-URL: Source Code, https://github.com/sphinx-toolbox/default_values
Project-URL: Documentation, https://default-values.readthedocs.io/en/latest
Platform: Windows
Platform: macOS
Platform: Linux
Classifier: Development Status :: 4 - Beta
Classifier: Framework :: Sphinx :: Extension
Classifier: Intended Audience :: Developers
Classifier: License :: OSI Approved :: MIT License
Classifier: Operating System :: OS Independent
Classifier: Programming Language :: Python
Classifier: Programming Language :: Python :: 3 :: Only
Classifier: Programming Language :: Python :: 3.7
Classifier: Programming Language :: Python :: 3.8
Classifier: Programming Language :: Python :: 3.9
Classifier: Programming Language :: Python :: 3.10
Classifier: Programming Language :: Python :: 3.11
Classifier: Programming Language :: Python :: 3.12
Classifier: Programming Language :: Python :: 3.13
Classifier: Programming Language :: Python :: Implementation :: CPython
Classifier: Programming Language :: Python :: Implementation :: PyPy
Classifier: Topic :: Documentation
Classifier: Topic :: Documentation :: Sphinx
Classifier: Topic :: Software Development :: Documentation
Classifier: Typing :: Typed
Requires-Python: >=3.7
Requires-Dist: docutils>=0.16
Requires-Dist: sphinx>=3.2.0
Requires-Dist: sphinx-jinja2-compat>=0.1.0
